b9y/__init__.py
b9y/bindings.py
b9y/dev-test.py
b9y/test.py
b9y-0.0.22.dist-info/LICENSE
b9y-0.0.22.dist-info/METADATA
b9y-0.0.22.dist-info/WHEEL
b9y-0.0.22.dist-info/top_level.txt
b9y-0.0.22.dist-info/RECORD
