Metadata-Version: 2.1
Name: b9y
Version: 0.0.22
Summary: Python Client for Bambleweeny, the HTTP based key-value store and message broker
Home-page: https://github.com/u1i/b9y-python
Author: Uli Hitzel
Author-email: uli.hitzel@gmail.com
License: UNKNOWN
Platform: UNKNOWN
Classifier: Programming Language :: Python :: 2
Classifier: Programming Language :: Python :: 3
Classifier: License :: OSI Approved :: MIT License
Classifier: Operating System :: OS Independent
Requires-Dist: requests
